README.rst
ropes.py
setup.cfg
setup.py
ropes.egg-info/PKG-INFO
ropes.egg-info/SOURCES.txt
ropes.egg-info/dependency_links.txt
ropes.egg-info/top_level.txt
test/test_ropes.py