Metadata-Version: 1.1
Name: ropes
Version: 0.1
Summary: A Python implementation of the Rope data structure
Home-page: http://github.com/marshallward/ropes
Author: Marshall Ward
Author-email: ropes@marshallward.org
License: UNKNOWN
Keywords: ropes,rope,string
Platform: UNKNOWN
Classifier: Development Status :: 1 - Planning
Classifier: License :: OSI Approved :: Apache Software License
Classifier: Programming Language :: Python
Classifier: Programming Language :: Python :: 2
Classifier: Programming Language :: Python :: 2.6
Classifier: Programming Language :: Python :: 2.7
Classifier: Programming Language :: Python :: 3
Classifier: Programming Language :: Python :: 3.2
Classifier: Programming Language :: Python :: 3.3
Classifier: Programming Language :: Python :: 3.4
Classifier: Programming Language :: Python :: 3.5
Classifier: Topic :: Utilities
